apepay/__init__.py
apepay/exceptions.py
apepay/factory.py
apepay/manager.py
apepay/manifest.json
apepay/package.py
apepay/py.typed
apepay/streams.py
apepay/utils.py
apepay/validators.py
apepay-0.3.9.dist-info/licenses/LICENSE
apepay-0.3.9.dist-info/METADATA
apepay-0.3.9.dist-info/WHEEL
apepay-0.3.9.dist-info/top_level.txt
apepay-0.3.9.dist-info/RECORD
