Metadata-Version: 2.4
Name: apepay
Version: 0.3.9
Summary: Python SDK for ApePay
Author-email: ApeWorX LTD <admin@apeworx.io>
License: Apache 2.0
Requires-Python: <4,>=3.10
License-File: LICENSE
Requires-Dist: eth-ape<1,>=0.8.24
Requires-Dist: pydantic<3,>=2.7
Provides-Extra: bot
Requires-Dist: silverback<1,>=0.7.13; extra == "bot"
Provides-Extra: lint
Requires-Dist: flake8; extra == "lint"
Requires-Dist: black; extra == "lint"
Requires-Dist: isort; extra == "lint"
Requires-Dist: mypy; extra == "lint"
Requires-Dist: apepay[bot]; extra == "lint"
Provides-Extra: test
Requires-Dist: ape-titanoboa>=0.8.0.a1; extra == "test"
Provides-Extra: dev
Requires-Dist: apepay[bot,lint,test]; extra == "dev"
Dynamic: license-file
